{"id":"y27vonm8r0jnk2zhs8uo7do","title":"Shenyang","desc":"","updated":1651045086225,"created":1651045086225,"custom":{},"fname":"censorship.subjects.pandemic.shenyang","type":"note","vault":{"fsPath":"vault"},"contentHash":"d0e409b6397e229d9d379efdbc24627c","links":[],"anchors":{"辟谣":{"type":"header","text":"\"辟谣\"","value":"辟谣","line":12,"column":0,"depth":2},"参考资料":{"type":"header","text":"参考资料","value":"参考资料","line":15,"column":0,"depth":2},"沈阳一男子因对防疫工作不满恶意骚扰辱骂110拘留":{"type":"header","text":"沈阳一男子因对防疫工作不满，恶意骚扰辱骂110，拘留","value":"沈阳一男子因对防疫工作不满恶意骚扰辱骂110拘留","line":17,"column":2,"depth":1}},"children":[],"parent":"ofqya32512pt1985hsxuk7c","data":{}}
